[{"id":1,"productName":"버그를 Java라 버그잡는 개리씨 키링 개발자키링 금속키링","price":12500,"stockCount":100,"thumbnailImg":"asset/img/thumbnailImg1.jpg","option":[],"discountRate":0,"shippingFee":1500,"detailInfoImage":["asset/img/detail/detail1-1.jpg","asset/img/detail/detail1-2.jpg"],"viewCount":2391,"pubDate":"2025-01-03","modDate":"2025-01-07"},{"id":2,"productName":"우당탕탕 라이캣의 실험실 스티커 팩","price":3500,"stockCount":1000,"thumbnailImg":"asset/img/thumbnailImg2.jpg","option":[],"discountRate":0,"shippingFee":1500,"detailInfoImage":["asset/img/detail/detail2-1.jpg","asset/img/detail/detail2-2.jpg"],"viewCount":30143,"pubDate":"2025-01-11","modDate":"2025-01-11"},{"id":3,"productName":"딥러닝 개발자 무릎 담요","price":17500,"stockCount":0,"thumbnailImg":"asset/img/thumbnailImg3.jpg","option":[],"discountRate":0,"shippingFee":1500,"detailInfoImage":["asset/img/detail/detail3-1.jpg","asset/img/detail/detail3-2.jpg","asset/img/detail/detail3-3.jpg"],"viewCount":4301,"pubDate":"2025-01-12","modDate":"2025-01-12"},{"id":4,"productName":"네 개발잡니다 개발자키링 금속키링","price":13500,"stockCount":100,"thumbnailImg":"asset/img/thumbnailImg4.jpg","option":[],"discountRate":0,"shippingFee":1500,"detailInfoImage":["asset/img/detail/detail4-1.jpg","asset/img/detail/detail4-2.jpg"],"viewCount":1231,"pubDate":"2025-01-13","modDate":"2025-01-13"},{"id":5,"productName":"Hack Your Life 개발자 노트북 파우치","price":36000,"stockCount":230,"thumbnailImg":"asset/img/thumbnailImg5.jpg","option":[{"id":1,"optionName":"13인치","additionalFee":0},{"id":2,"optionName":"15인치","additionalFee":1000}],"discountRate":19,"shippingFee":1500,"detailInfoImage":["asset/img/detail/detail5-1.jpg","asset/img/detail/detail5-2.jpg"],"viewCount":324,"pubDate":"2025-02-01","modDate":"2025-05-11"},{"id":6,"productName":"[NEW] 위니브 개발자, 캐릭터 스티커팩 2종","price":5500,"stockCount":1000,"thumbnailImg":"asset/img/thumbnailImg6.jpg","option":[{"id":1,"optionName":"위니브 개발자 스티커팩","additionalFee":0},{"id":2,"optionName":"위니브 프랜즈 스티커팩","additionalFee":0},{"id":3,"optionName":"스티커팩 세트(개발자+프렌즈)","additionalFee":5000}],"discountRate":0,"shippingFee":1500,"detailInfoImage":["asset/img/detail/detail6-1.jpg","asset/img/detail/detail6-2.jpg"],"viewCount":103,"pubDate":"2025-04-11","modDate":"2025-04-11"},{"id":7,"productName":"제주코딩베이스캠프 코딩 연습장 세트","price":8000,"stockCount":1000,"thumbnailImg":"asset/img/thumbnailImg7.jpg","option":[],"discountRate":0,"shippingFee":1500,"detailInfoImage":["asset/img/detail/detail7-1.jpg","asset/img/detail/detail7-2.jpg"],"viewCount":5970,"pubDate":"2025-05-10","modDate":"2025-05-13"}]